shifre/__init__.py
shifre/shifre.py
shifre-0.1.2.dist-info/LICENSE
shifre-0.1.2.dist-info/METADATA
shifre-0.1.2.dist-info/WHEEL
shifre-0.1.2.dist-info/top_level.txt
shifre-0.1.2.dist-info/RECORD
