Metadata-Version: 2.1
Name: shifre
Version: 0.1.2
Summary: Shifre is a Python password generator library.
Home-page: https://github.com/yvztzgl/shifre
Author: Yavuz Tezgel
Author-email: yavuztzgl@gmail.com
License: UNKNOWN
Keywords: python,password,password generator,secure password,security,secure,generator
Platform: UNKNOWN
Classifier: Development Status :: 1 - Planning
Classifier: Intended Audience :: Developers
Classifier: Programming Language :: Python :: 3
Classifier: Operating System :: Unix
Classifier: Operating System :: MacOS :: MacOS X
Classifier: Operating System :: Microsoft :: Windows
License-File: LICENSE
